{
    "WXPay_faceid_leg": "ຂໍ້ຕົກລົງການບໍລິການຢັ້ງຢືນຕົວຕົນຈາກຮອຍໃບໜ້າ Weixin Pay",
    "Tencent_news": "Tencent News",
    "Wecoin_recharge_leg": "ຂໍ້ຕົກລົງການຕື່ມເງິນຂອງ WeBeans",
    "Tencent_cloud": "Tencent Cloud",
    "WXChannels_rewards_leg": "ຂໍ້ກໍານົດການນໍາໃຊ້ຄຸນສົມບັດລາງວັນການຖ່າຍທອດໃນຊ່ອງ Weixin",
    "WXChannels_live_leg": "ມາດຕະຖານການປະພຶດໃນການຖ່າຍທອດສົດໃນຊ່ອງຂອງ Weixin",
    "BRAND_for_Auto": "Weixin for Auto",
    "Domestic_user_leg": "ນະໂຍບາຍການໃຊ້ທີ່ເປັນທີ່ຍອມຮັບຂອງ WeChat",
    "Tencent_Miaojian": "Tencent Miaojian",
    "BRAND_Games": "ເກມ Weixin",
    "BRAND_Copyright_Prefix": "WeChat 版权所有",
    "WeBeans_leg2": "ຂໍ້ກໍານົດການນໍາໃຊ້ WeBeans ແລະ ຄຸນສົມບັດທີ່ກ່ຽວຂ້ອງ",
    "Overseas_user_leg": "ນະໂຍບາຍການໃຊ້ທີ່ເປັນທີ່ຍອມຮັບຂອງ WeChat",
    "WeBeans_leg1": "ຂໍ້ກໍານົດການນໍາໃຊ້ WeBeans",
    "WXPay_leg": "ຂໍ້ຕົກລົງການບໍລິການຜູ້ໃຊ້ Weixin Pay",
    "Tencent_meeting": "Tencent Meeting",
    "WXPay_carowner_leg": "ຂໍ້ຕົກລົງການບໍລິການເຈົ້າຂອງລົດ Weixin",
    "BRAND_for_Windows": "WeChat for Windows",
    "Domestic_serv_leg": "WeChat - ຂໍ້ກຳນົດຂອງການບໍລິການ",
    "BRAND_Official_Account": "ບັນຊີທາງການ Weixin",
    "BRAND_Index": "ດັດຊະ\u200bນີ Weixin",
    "wx_wc": "Weixin/WeChat",
    "WXPay_face_leg": "ຂໍ້ຕົກລົງການບໍລິການຈ່າຍເງິນດ້ວຍການກວດຫາໃບໜ້າ Weixin Pay",
    "BRAND_hongbao": "ອັ່ງເປົາ Weixin",
    "BRAND_Transfer_Oversea": "ໂອນເງິນ WeChat",
    "BRAND_for_Mac1": "WeChat for Mac",
    "BRAND_Balance": "ຍອດ\u200bເຫຼືອໃນ Weixin",
    "WXChannels_live_terms": "ຂໍ້ກໍານົດການນໍາໃຊ້ຄຸນສົມບັດການຖ່າຍທອດສົດຂອງຊ່ອງ Weixin",
    "BRAND_Wallet": "ກະເປົາເງິນ Weixin",
    "BRAND_for_Desktop": "WeChat ສຳລັບເດສ໌ທ໋ອບ",
    "Overseas_priv_leg": "ນະໂຍບາຍຄວາມເປັນສ່ວນຕົວຂອງ WeChat",
    "Brand_for_Apple_Watch": "Wexin for Apple Watch",
    "BRAND_for_Web4": "WeChat for Web",
    "BRAND_for_iPad1": "WeChat for iPad",
    "BRAND_for_Web5": "WeChat for Web",
    "Tencent_video": "Tencent Video",
    "BRAND_for_Web2": "WeChat for Web",
    "BRAND_for_iPad2": "WeChat for iPad",
    "BRAND_for_Web3": "WeChat for Web",
    "WXChannels_live_banleg": "ມາດຕະຖານການໂພສຂໍ້ມູນທາງການຕະຫຼາດດ້ວຍຄຸນສົມບັດຖ່າຍທອດສົດໃນຊ່ອງຂອງ Weixin",
    "BRAND_for_Web1": "WeChat for Web",
    "BRAND_Split_Bill_Oversea": "ແບ່ງກັນຈ່າຍໃນ WeChat",
    "BRAND_Pay_Score": "ຄະແນນ Weixin Pay",
    "WeCom": "WeCom",
    "BRAND_Teen": "ເຍົາວະຊົນ",
    "WXTeenMode_reg": "ຂໍ້ກໍານົດການນໍາໃຊ້ຄຸນສົມບັດໂໝດຜູ້ປົກຄອງຂອງ WeChat",
    "BRAND_Open_Platform": "ແພລດຟອມເປີດຂອງ Weixin",
    "BRAND_Balance_Oversea": "ຍອດ\u200bເຫຼືອໃນ WeChat",
    "WeCom_Business_Card": "ນາມບັດ WeCom",
    "We_Beans": "WeBeans",
    "BRAND_Official_Accounts_R": "ບັນ\u200bຊີ\u200bທາງ\u200bການ Weixin",
    "WXChanels_ban_overview": "ພາບລວມເນື້ອຫາຊ່ອງທີ່ບໍ່ສອດຄ່ອງກັບລະບຽບແບບທົ່ວໄປ",
    "WXOpen_dev_leg": "ຂໍ້ຕົກລົງການບໍລິການຂອງຜູ້ພັດທະນາແພລດຟອມ Weixin ແບບເປີດ",
    "BRAND_for_Windows1": "WeChat for Windows",
    "BRAND_Translate": "Weixin Translate",
    "BRAND_kids_account": "ID ຂອງ Weixin ສໍາລັບໂມງເດັກນ້ອຍ",
    "BRAND_Copyright_Suffix": "WeChat",
    "Tencent_game": "Tencent Games",
    "BRAND_Out": "WeChat Out",
    "Tencent_live": "Tencent Live",
    "BRAND_ID_Others": "ID",
    "WXPay_life_leg": "ຂໍ້ຕົກລົງການບໍລິການຫັກເງິນແບບອັດຕະໂນມັດຂອງ WeChat Pay ສໍາລັບເຄື່ອງໃຊ້ສາທາລະນຸປະໂພກ",
    "BRAND_Cashier_Assistant": "ຜູ້ຊ່ວຍຮັບເງິນຂອງ Weixin",
    "BRAND_EasyMode": "ໂໝດງ່າຍຂອງ Weixin",
    "Domestic_privacy_leg": "ນະໂຍບາຍຄວາມເປັນສ່ວນຕົວຂອງ WeChat",
    "BRAND_Movie_Tickets": "ປີ້ຮູບເງົາ Weixin",
    "BRAND_Scan_Payment_Oversea": "ການຈ່າຍເງິນແບບສະແກນຂອງ WeChat",
    "BRAND_Pay_OverseaHK": "WeChat Pay HK",
    "BRAND_Credit_Card": "ບັດເຄຣດິດ Weixin",
    "WX_locationmark_leg": "ຂໍ້ຕົກລົງກາຍໝາຍສະຖານທີ່ຕັ້ງຂອງ Weixin",
    "BRAND_Photo_Frame": "ຂອບຮູບ WeChat",
    "BRAND_Top_Stories": "ເລື່ອງລາວຍອດນິຍົມຂອງ Weixin",
    "Compliance_Terms": "WeChat - ຂໍ້ກຳນົດຂອງການບໍລິການ",
    "WXplus_leg": "ຂໍ້ກໍານົດການນໍາໃຊ້ສໍາລັບ Weixin Plus",
    "BRAND_Split_Bill": "\u200bບິນແຍກໃນ Weixin",
    "WXlink_leg": "ມາດຕະການຄຸ້ມຄອງເນື້ອຫາລິ້ງພາຍນອກຂອງ Weixin",
    "WX_easymode_leg": "ຂໍ້ກໍານົດການນໍາໃຊ້ຄຸນສົມບັດໂໝດງ່າຍຂອງ Weixin",
    "Tencent_translator": "Mr. Translator",
    "BRAND_Scan_Payment": "ການຈ່າຍເງິນແບບສະແກນຂອງ Weixin",
    "Tencent_kingcard": "Tencent King Card",
    "Brand_for_Kids_Watch1": "Weixin for Kids' Watch",
    "BRAND_Pay": "Weixin Pay",
    "BRAND_TeenMode": "ໂໝດຜູ້ປົກຄອງ",
    "WeRead": "WeRead",
    "WXOA_op_leg": "ຂໍ້ແນະນໍາການດໍາເນີນງານຂອງແພລດຟອມບັນຊີທາງການ Weixin",
    "BRAND_for_Mac": "WeChat for Mac",
    "Tenpay_priv_leg": "ນະໂຍບາຍຄວາມເປັນສ່ວນຕົວ Tenpay",
    "WXOpen_op_leg": "ກົດລະບຽບການດໍາເນີນງານຂອງແພລດຟອມໂປຣແກຣມຂະໜາດນ້ອຍຂອງ Weixin",
    "BRAND_fapiao": "Weixin fapiao",
    "BRAND_Pay_Oversea": "WeChat Pay",
    "OfficialEntity_Service": "ຝ່າຍບໍລິການລູກຄ້າຂອງ WeChat",
    "WXgrouplive_leg": "ຂໍ້ກໍານົດການນໍາໃຊ້ຄຸນສົມບັດການຖ່າຍທອດສົດໃນກຸ່ມ Weixin",
    "We_Run": "WeRun",
    "Tencent_music": "Tencent Music",
    "BRAND_Credit_Card_Oversea": "ບັດເຄຣດິດ WeChat",
    "WXPay_ebiz_leg": "ຂໍ້ກໍານົດການບໍລິການການຄ້າອີເລັກໂທຣນິກ Weixin",
    "WX_group_leg": "ຂໍ້ແນະນໍາສໍາລັບການນໍາໃຊ້ຂອງກຸ່ມ Weixin",
    "BRAND": "WeChat",
    "Wi-Fi_via_BRAND": "Wi-Fi ຜ່ານ Weixin",
    "WXPay_card_leg": "ຂໍ້ຕົກລົງຜູ້ໃຊ້ວ່າດ້ວຍບັດເຄຣດິດ Weixin",
    "Cards_and_Offers": "ບັດ ແລະ ຂໍ້ສະເໜີຂອງ Weixin",
    "BRAND_Services": "Weixin Plus",
    "WXinfringe_leg": "ຂໍ້ແນະນໍາກ່ຽວກັບການແຈ້ງເຕືອນໂຕ້ຕອບສໍາລັບການລາຍງານຂອງຜູ້ໃຊ້ Weixin ລາຍບຸກຄົນຕໍ່ການລະເມີດສິດ",
    "wxp_wcp": "Weixin Pay/WeChat Pay",
    "Tencent_docs": "Tencent Docs",
    "BRAND_Movie_Tickets_Oversea": "ປີ້ຮູບເງົາ WeChat",
    "BRAND_Official_Accounts": "ບັນ\u200bຊີ\u200bທາງ\u200bການ Weixin",
    "WXChannels_webeans_leg_viewer": "ຂໍ້ຕົກລົງວ່າດ້ວຍຄຸນສົມບັດການຖ່າຍທອດສົດທີ່ຈ່າຍດ້ວຍ WeBeans ຂອງຊ່ອງ Weixin (ສໍາລັບຜູ້ຊົມ)",
    "WXChannels_verify_leg": "ຂໍ້ກໍານົດການບໍລິການຢັ້ງຢືນຊ່ອງ Weixin",
    "Watch_BRAND": "WeChat for Watch",
    "Cards_and_Offers_Oversea": "ບັດ ແລະ ຂໍ້ສະເໜີຂອງ WeChat",
    "BRAND_Team": "ທີມ Weixin",
    "BRAND_hongbao_Oversea": "ອັ່ງເປົາ WeChat",
    "Tencent_pcmanager": "Tencent PC Manager",
    "BRAND_Moments": "ຊ່ວງເວລາທີ່ສໍາຄັນໃນ Weixin",
    "BRAND_Pay_OverseaMY": "WeChat Pay MY",
    "WXChannels_live_banlist": "ລາຍການຂໍ້ມູນທາງການຕະຫຼາດທີ່ຖືກຫ້າມໂດຍຄຸນສົມບັດກາຍຖ່າຍທອດສົດໃນຊ່ອງ Weixin",
    "Channels": "ຊ່ອງ",
    "WXChannels_leg": "ມາດຕະຖານການດໍາເນີນງານຊ່ອງຂອງ Weixin",
    "WeCom_priv_leg": "ຂໍ້ແນະນໍາກ່ຽວກັບການປົກປ້ອງຄວາມເປັນສ່ວນຕົວ WeCom",
    "BRAND_ID": "ID ຂອງ WeChat",
    "WXOA_serve_leg": "ແພລດຟອມບໍລິຫານບັນຊີທາງການ Weixin - ຂໍ້ກໍານົດການບໍລິການ",
    "Tencent_mobility": "Tencent Mobility",
    "OfficialAliasName": "WeChat",
    "WXPay_trust_leg": "ຂໍ້ຕົກລົງການຈ່າຍຄ່າຊັບສິນຂອງ Weixin Pay",
    "Tencent_map": "Tencent Maps",
    "BRAND_for_Windows_10": "WeChat for Windows 10",
    "BRAND_Channels": "ຊ່ອງ Weixin",
    "Tentcent_tengan": "Tencent Tengan",
    "BRAND_for_QQ_Browser": "WeChat for QQ Browser",
    "Tencent_weibo": "Tencent Weibo",
    "BRAND_Wallet_Oversea": "ກະເປົາເງິນ WeChat",
    "Tencent_security": "Tencent Security",
    "BRAND_kids": "ເດັກນ້ອຍໃນ Weixin",
    "OfficialEntity": "WeChat International Pte. Ltd.",
    "BRAND_Transfer": "ໂອນເງິນ Weixin",
    "BRAND_Security_Alert": "ແຈ້ງເຕືອນດ້ານຄວາມປອດໄພຂອງ WeChat",
    "WXKids_watch_leg": "ຂໍ້ກໍານົດການນໍາໃຊ້ Weixin ສໍາລັບເດັກນ້ອຍ",
    "WXChannels_webeans_leg_host": "ຂໍ້ຕົກລົງວ່າດ້ວຍຄຸນສົມບັດການຖ່າຍທອດສົດທີ່ຈ່າຍດ້ວຍ WeBeans ຂອງຊ່ອງ Weixin (ສໍາລັບໂຮສ)",
    "Brand_for_Kids_Watch": "Weixin for Kids' Watch",
    "BRAND_Security_Center": "ສູນຄວາມ\u200bປອດ\u200bໄພ WeChat",
    "BRAND_Headset": "ຫູຟັງສໍາລັບ Weixin",
    "WXOAint_serve_leg": "ຂໍ້ຕົກລົງການບໍລິການຂອງແພລດຟອມບັນຊີທາງການ Weixin",
    "WXOpen_serve_leg": "ຂໍ້ກໍານົດການນໍາໃຊ້ແພລດຟອມໂປຣແກຣມຂະໜາດນ້ອຍຂອງ Weixin"
}