{"v":"5.6.6","ip":0,"op":1,"fr":60,"w":24,"h":24,"layers":[{"ind":963,"nm":"surface2745","ao":0,"ip":0,"op":60,"st":0,"ty":4,"ks":{"ty":"tr","o":{"k":100},"r":{"k":0},"p":{"k":[0,0]},"a":{"k":[0,0]},"s":{"k":[133.33,133.33]},"sk":{"k":0},"sa":{"k":0}},"shapes":[{"ty":"gr","hd":false,"nm":"surface2745","it":[{"ty":"gr","hd":false,"it":[{"ty":"sh","ks":{"k":{"i":[[0,0],[0,0],[0,0],[0,0],[0,0],[0,0],[0,0],[0,0],[0,0],[0,0],[0,0],[0,0]],"o":[[0,0],[0,0],[0,0],[0,0],[0,0],[0,0],[0,0],[0,0],[0,0],[0,0],[0,0],[0,0]],"v":[[9,9.71],[5.96,12.75],[5.25,12.04],[8.29,9],[5.25,5.96],[5.96,5.25],[9,8.29],[12.04,5.25],[12.75,5.96],[9.71,9],[12.75,12.04],[12.04,12.75]],"c":true}}},{"ty":"fl","o":{"k":100},"c":{"k":[0,0,0,1]}},{"ty":"tr","o":{"k":100},"r":{"k":0},"p":{"k":[0,0]},"a":{"k":[0,0]},"s":{"k":[100,100]},"sk":{"k":0},"sa":{"k":0},"hd":false}]},{"ty":"gr","hd":false,"it":[{"ty":"sh","ks":{"k":{"i":[[0,0],[4.97,0],[0,4.97],[-4.97,0],[0,-4.97]],"o":[[0,4.97],[-4.97,0],[0,-4.97],[4.97,0],[0,0]],"v":[[18,9],[9,18],[0,9],[9,0],[18,9]],"c":false}}},{"ty":"fl","o":{"k":100},"c":{"k":[1,1,1,1]}},{"ty":"tr","o":{"k":100},"r":{"k":0},"p":{"k":[0,0]},"a":{"k":[0,0]},"s":{"k":[100,100]},"sk":{"k":0},"sa":{"k":0},"hd":false}]},{"ty":"tr","o":{"k":100},"r":{"k":0},"p":{"k":[0,0]},"a":{"k":[0,0]},"s":{"k":[100,100]},"sk":{"k":0},"sa":{"k":0},"hd":false}]}]}],"meta":{"g":"LF SVG to Lottie"},"assets":[]}